hyh/__init__.py
hyh/__main__.py
hyh/acp.py
hyh/client.py
hyh/daemon.py
hyh/demo.py
hyh/git.py
hyh/init.py
hyh/plan.py
hyh/py.typed
hyh/registry.py
hyh/runtime.py
hyh/state.py
hyh/trajectory.py
hyh/workflow.py
hyh/worktree.py
hyh/plugin/plugin.json
hyh/plugin/commands/help.md
hyh/plugin/commands/hyh.md
hyh/plugin/hooks/hooks.json
hyh/plugin/skills/spec-driven-dev.md
hyh/templates/checklist-template.md
hyh/templates/plan-template.md
hyh/templates/spec-template.md
hyh/templates/tasks-template.md
hyh-0.1.0a5.dist-info/METADATA
hyh-0.1.0a5.dist-info/WHEEL
hyh-0.1.0a5.dist-info/entry_points.txt
hyh-0.1.0a5.dist-info/licenses/LICENSE
hyh-0.1.0a5.dist-info/RECORD
