Metadata-Version: 2.4
Name: hyh
Version: 0.1.0a5
Summary: CLI orchestration tool for agentic workflows - coordinate tasks with claude-code and other AI agents
Project-URL: Homepage, https://github.com/pproenca/hyh
Project-URL: Documentation, https://github.com/pproenca/hyh#readme
Project-URL: Repository, https://github.com/pproenca/hyh.git
Project-URL: Issues, https://github.com/pproenca/hyh/issues
Project-URL: Changelog, https://github.com/pproenca/hyh/releases
Project-URL: Funding, https://github.com/sponsors/pproenca
Author-email: Pedro Proenca <pedro@10xengs.com>
License-Expression: MIT
License-File: LICENSE
Keywords: agents,claude-code,cli,daemon,orchestration,tasks,unix-socket,workflow
Classifier: Development Status :: 4 - Beta
Classifier: Environment :: Console
Classifier: Intended Audience :: Developers
Classifier: License :: OSI Approved :: MIT License
Classifier: Operating System :: MacOS
Classifier: Operating System :: POSIX :: Linux
Classifier: Programming Language :: Python :: 3
Classifier: Programming Language :: Python :: 3.13
Classifier: Programming Language :: Python :: 3.14
Classifier: Topic :: Software Development :: Libraries :: Python Modules
Classifier: Topic :: System :: Distributed Computing
Classifier: Typing :: Typed
Requires-Python: >=3.13
Requires-Dist: defusedxml>=0.7.1
Requires-Dist: msgspec>=0.18
